jeeves/__init__.py
jeeves/__main__.py
jeeves/alteration.py
jeeves/app_utils.py
jeeves/application.py
jeeves/audioengine.py
jeeves/batch_mic.py
jeeves/brain.py
jeeves/conversation.py
jeeves/diagnose.py
jeeves/i18n.py
jeeves/local_mic.py
jeeves/mic.py
jeeves/notifier.py
jeeves/paths.py
jeeves/plugin.py
jeeves/pluginstore.py
jeeves/populate.py
jeeves/testutils.py
jeeves/vocabcompiler.py
jeeves/data/audio/beep_hi.wav
jeeves/data/audio/beep_lo.wav
jeeves/data/audio/jasper.wav
jeeves/data/audio/say.wav
jeeves/data/audio/time.wav
jeeves/data/locale/de-DE.po
jeeves/data/locale/en-US.po
jeeves/data/locale/fr-FR.po
jeeves/data/standard_phrases/de-DE.txt
jeeves/data/standard_phrases/en-US.txt
jeeves_pa-0.0.4.data/data/share/doc/jeeves/LICENSE.md
jeeves_pa-0.0.4.data/data/share/doc/jeeves/README.md
jeeves_pa-0.0.4.dist-info/DESCRIPTION.rst
jeeves_pa-0.0.4.dist-info/METADATA
jeeves_pa-0.0.4.dist-info/RECORD
jeeves_pa-0.0.4.dist-info/WHEEL
jeeves_pa-0.0.4.dist-info/entry_points.txt
jeeves_pa-0.0.4.dist-info/metadata.json
jeeves_pa-0.0.4.dist-info/top_level.txt
plugins/audioengine/alsa-ae/__init__.py
plugins/audioengine/alsa-ae/alsaaudioengine.py
plugins/audioengine/alsa-ae/plugin.info
plugins/audioengine/pyaudio-ae/__init__.py
plugins/audioengine/pyaudio-ae/plugin.info
plugins/audioengine/pyaudio-ae/pyaudioengine.py
plugins/speechhandler/birthday/__init__.py
plugins/speechhandler/birthday/birthday.py
plugins/speechhandler/birthday/plugin.info
plugins/speechhandler/birthday/locale/de-DE.po
plugins/speechhandler/birthday/locale/en-US.po
plugins/speechhandler/birthday/locale/fr-FR.po
plugins/speechhandler/clock/__init__.py
plugins/speechhandler/clock/clock.py
plugins/speechhandler/clock/plugin.info
plugins/speechhandler/clock/test_clock.py
plugins/speechhandler/clock/locale/de-DE.po
plugins/speechhandler/clock/locale/en-US.po
plugins/speechhandler/clock/locale/fr-FR.po
plugins/speechhandler/gmail/__init__.py
plugins/speechhandler/gmail/gmail.py
plugins/speechhandler/gmail/plugin.info
plugins/speechhandler/gmail/test_gmail.py
plugins/speechhandler/gmail/locale/de-DE.po
plugins/speechhandler/gmail/locale/en-US.po
plugins/speechhandler/gmail/locale/fr-FR.po
