Metadata-Version: 2.0
Name: jeeves-pa
Version: 0.0.4
Summary: Jeeves is an open source platform for developing always-on, voice-controlled applications.
Home-page: http://github.com/narfman0/jeeves/
Author: Jon Robison
Author-email: narfman0@gmail.com
License: MIT
Platform: UNKNOWN
Requires-Dist: APScheduler
Requires-Dist: PyYAML
Requires-Dist: argparse
Requires-Dist: mad
Requires-Dist: python-slugify
Requires-Dist: pytz
Requires-Dist: requests
